xverse/__init__.py
xverse/feature_subset.py
xverse/ensemble/__init__.py
xverse/ensemble/_voting.py
xverse/graph/__init__.py
xverse/graph/_bivariate_charts.py
xverse/transformer/__init__.py
xverse/transformer/_binning.py
xverse/transformer/_woe.py
xverse-1.0.5.dist-info/LICENSE.md
xverse-1.0.5.dist-info/METADATA
xverse-1.0.5.dist-info/WHEEL
xverse-1.0.5.dist-info/top_level.txt
xverse-1.0.5.dist-info/RECORD
