Metadata-Version: 2.1
Name: xverse
Version: 1.0.5
Summary: xverse short for X uniVerse is collection of transformers for feature engineering and feature selection
Home-page: https://github.com/Sundar0989/XuniVerse
Author: Sundar Krishnan
Author-email: sundarstyles89@gmail.com
License: MIT
Platform: UNKNOWN
Classifier: Programming Language :: Python :: 3
Classifier: License :: OSI Approved :: MIT License
Classifier: Operating System :: OS Independent
Requires-Python: >=3.5.*
